gptzip/__init__.py
gptzip/gptzip.py
gptzip/helpers.py
gptzip/utils.py
gptzip-0.0.2.dist-info/LICENSE
gptzip-0.0.2.dist-info/METADATA
gptzip-0.0.2.dist-info/WHEEL
gptzip-0.0.2.dist-info/top_level.txt
gptzip-0.0.2.dist-info/RECORD
