Metadata-Version: 2.1
Name: gptzip
Version: 0.0.2
Summary: losslessly compress data with language models
Author: Jack Morris
Author-email: jxm3@cornell.edu
License-File: LICENSE
Requires-Dist: tqdm
Requires-Dist: transformers
